kicad_symbol_merge/__init__.py
kicad_symbol_merge/merge.py
kicad_symbol_merge-0.2.0.dist-info/licenses/LICENSE
kicad_symbol_merge-0.2.0.dist-info/METADATA
kicad_symbol_merge-0.2.0.dist-info/WHEEL
kicad_symbol_merge-0.2.0.dist-info/entry_points.txt
kicad_symbol_merge-0.2.0.dist-info/top_level.txt
kicad_symbol_merge-0.2.0.dist-info/RECORD
