Metadata-Version: 2.4
Name: kicad-symbol-merge
Version: 0.2.0
Summary: Merge all .kicad_sym symbol files in a folder into one KiCad library (KiCad v6+ compatible).
Author-email: Justin Sapun <jsapun24@email.com>
License: MIT
Project-URL: Homepage, https://github.com/jsapun/kicad-symbol-merge
Project-URL: Source, https://github.com/jsapun/kicad-symbol-merge
Project-URL: Issues, https://github.com/jsapun/kicad-symbol-merge/issues
Requires-Python: >=3.7
License-File: LICENSE
Dynamic: license-file
